<?xml version="1.0" encoding="UTF-8"?>
<!--
    This XML file provides all the text to be used when the application
    is to be displayed in English.
-->
<properties>
    <property_list>

        <!-- ENGLISH LANGUAGE SETTINGS FOR DESKTOP JAVA FRAMEWORK CONTROLS -->

        <!-- WELCOME DIALOG TEXT -->
        <property name="WELCOME_DIALOG_TITLE"               value="nuqneH mIw'e' rep"></property>
        <property name="WELCOME_DIALOG_RECENT_WORK_LABEL"   value="recent Qap"></property>
        <property name="WELCOME_DIALOG_NEW_BUTTON_TEXT"  value="rep mIw'e' chu' chenmoH"></property>

        <!-- GENERIC APP ERROR MESSAGES -->
        <property name="APP_ERROR_TITLE"            value="application Qagh"></property>
        <property name="APP_ERROR_CONTENT"          value="Qagh occured neH Application"></property>

        <!-- PROPERTIES ERROR MESSAGES -->
        <property name="PROPERTIES_ERROR_TITLE"     value="bang teywI' Qagh"></property>
        <property name="PROPERTIES_ERROR_CONTENT"   value="tu'lu' Qagh Loading bang teywI'"></property>

        <!-- FILE TOOLBAR TOOLTIPS -->
        <property name="NEW_BUTTON_TOOLTIP"         value="rep mIw'e' chu'"></property>
        <property name="LOAD_BUTTON_TOOLTIP"        value="load mIw'e' rep"></property>
        <property name="CLOSE_BUTTON_TOOLTIP"       value="SoQ mIw'e' rep"></property>
        <property name="SAVE_BUTTON_TOOLTIP"        value="mIw'e' rep toD"></property>
        <property name="EXPORT_BUTTON_TOOLTIP"      value="export mIw'e' rep"></property>
        <property name="EXIT_BUTTON_TOOLTIP"        value="mej"></property>

        <!-- CLIPBOARD TOOLBAR TOOLTIPS -->
        <property name="CUT_BUTTON_TOOLTIP"         value="chIp"></property>
        <property name="COPY_BUTTON_TOOLTIP"        value="copy"></property>
        <property name="PASTE_BUTTON_TOOLTIP"       value="paste"></property>

        <!-- UNDO TOOLBAR TOOLTIPS -->
        <property name="UNDO_BUTTON_TOOLTIP"        value="Ha'"></property>
        <property name="REDO_BUTTON_TOOLTIP"        value="redo"></property>

        <!-- HELP TOOLBAR TOOLTIPS -->
        <property name="HELP_BUTTON_TOOLTIP"        value="QaH"></property>
        <property name="LANGUAGE_BUTTON_TOOLTIP"    value="choH langauge"></property>
        <property name="ABOUT_BUTTON_TOOLTIP"       value="umqu' ghot"></property>

        <!-- NEW FEEDBACK DIALOGS -->	
        <property name="NEW_SUCCESS_TITLE"      value="chu' naQ"></property>
        <property name="NEW_SUCCESS_CONTENT"	value="Qap chenmoH 'ach wej toD"></property>
        <property name="NEW_ERROR_TITLE"        value="ghuHmoH: Qagh"></property>
        <property name="NEW_ERROR_CONTENT"      value="chenmoH chu' Qap qaS Qagh."></property>

        <!-- LOAD FEEDBACK DIALOGS -->
        <property name="LOAD_WORK_TITLE"        value="Qap load"></property>
        <property name="LOAD_SUCCESS_TITLE"     value="load naQmoH wanI'mey"></property>
        <property name="LOAD_SUCCESS_CONTENT"   value="chaq Loaded Successfully 'ej laH DaH edited teywI'."></property>
        <property name="LOAD_ERROR_TITLE"       value="Qagh loading"></property>        
        <property name="LOAD_ERROR_CONTENT"     value="luj loading. ghaytan pa' qay' teywI' Formating."></property>

        <!-- SAVE FEEDBACK DIALOGS -->
        <property name="SAVE_WORK_TITLE"        value="Qap toD"></property>
        <property name="SAVE_SUCCESS_TITLE"     value="toD naQmoH wanI'mey"></property>
        <property name="SAVE_SUCCESS_CONTENT"   value="yemwI' teywI'."></property>
        <property name="SAVE_ERROR_TITLE"       value="yemwI' teywI'."></property>
        <property name="SAVE_ERROR_CONTENT"     value="luj saving. ghaytan muHIvtaHbogh teywI' naw' qay''a'."></property>
        <property name="SAVE_VERIFY_TITLE"	value="toD, unsave vum?"></property>
        <property name="SAVE_VERIFY_CONTENT"	value="unsave Qu'lIj toD wa'DIch rur SoH?"></property>

        <!-- ABOUT DIALOG -->
        <property name="ABOUT_TITLE"            value="vIHtaHbogh majQa'"></property>
        <property name="ABOUT_CONTENT"          value="OH, the Office Hours Manager - Debugging Enterprises - © 2018"></property>


        <!-- ENGLISH LANGUAGE SETTINGS SPECIFICALLY FOR TDLM CONTROLS -->

        <!-- LANGUAGE-DEPENDENT TEXT FOR OH WORKSPACE CONTROLS -->
        <property name="OH_TAS_HEADER_LABEL_TEXT"           value="paQDI'norgh boQwI'"></property>
        <property name="OH_NAME_TEXT_FIELD_PROMPT_TEXT"            value="pong"></property>
        <property name="OH_EMAIL_TEXT_FIELD_PROMPT_TEXT"           value="email"></property>
        <property name="OH_ADD_TA_BUTTON_TEXT"              value="CHEL TA"></property>
        <property name="OH_OFFICE_HOURS_HEADER_LABEL_TEXT"  value="mIw'e' rep"></property>
        <property name="OH_NAME_TABLE_COLUMN_TEXT"          value="pong"></property>
        <property name="OH_EMAIL_TABLE_COLUMN_TEXT"         value="email"></property>
        <property name="OH_SLOTS_TABLE_COLUMN_TEXT"         value="poH Slots"></property>
        <property name="OH_START_TIME_TABLE_COLUMN_TEXT"    value="start poH"></property>
        <property name="OH_END_TIME_TABLE_COLUMN_TEXT"      value="'o'megh poH"></property>
        <property name="OH_MONDAY_TABLE_COLUMN_TEXT"        value="monday"></property>
        <property name="OH_TUESDAY_TABLE_COLUMN_TEXT"       value="tuesday"></property>
        <property name="OH_WEDNESDAY_TABLE_COLUMN_TEXT"     value="wednesday"></property>
        <property name="OH_THURSDAY_TABLE_COLUMN_TEXT"      value="thursday"></property>
        <property name="OH_FRIDAY_TABLE_COLUMN_TEXT"        value="friday"></property>
        <property name="S_FONT_LABEL_TEXT"                  value="askjfkj asfj wjf:"></property>
        <property name="S_NOTE_LABEL_TEXT"                  value="Note: sfgrf Debe colocarse dentro de work / css para ser seleccionable"></property>
        
        <property name="CSG_SITE_TAB"                       value="sitio"></property>
        <property name="CSG_SYLLABUS_TAB"                   value="silaba"></property>
        <property name="CSG_MT_TAB"                         value="Horarios de Reuniones"></property>
        <property name="CSG_OH_TAB"                         value="mIw'e' rep"></property>
        <property name="CSG_SCHEDULE_TAB"                   value="Horas de oficina"></property>
        <property name="MT_LECTURE_LABEL_TEXT"                   value="Conferencia"></property>
        <property name="MT_RECITATION_LABEL_TEXT"                value="Recitación"></property>
        <property name="MT_LABS_LABEL_TEXT"                      value="Laboratorios"></property>
        <property name="S_HOME_CHECK_BOX"                    value="juH"></property>
        <property name="S_SYLLABUS_CHECK_BOX"                value="syllabus"></property>
        <property name="S_SCHEDULE_CHECK_BOX"                value="schedule"></property>
        <property name="S_HWS_CHECK_BOX"                     value="HWs"></property>
        
        <property name="S_PAGES_LABEL_TEXT"                 value="Páginas"></property>
        <property name="S_HWS_LABEL_TEXT"                   value="HWS"></property>
        <property name="S_SCHEDULE_LABEL_TEXT"              value="Programar"></property>
        <property name="S_SYLLABUS_LABEL_TEXT"              value="Silaba"></property>
        <property name="S_HOME_LABEL_TEXT"                  value="Casa"></property>
        
        <property name="OH_NO_SELECTED_TITLE_TEXT"           value="No TA SELECCIONADA"></property>
        <property name="OH_NO_SELECTED_CONTENT_TEXT"         value="No TA SELECCIONADA"></property>
        <property name="OH_REMOVE_TA_BUTTON_TEXT"             value="-"></property>
        <property name="CALENDAR_LABEL_TEXT"                  value="Límites del calendario"></property>
        <property name="START_LABEL_TEXT"                     value="A partir del lunes:"></property>
        <property name="END_LABEL_TEXT"                       value="Terminando el viernes:"></property>
        
        <property name="ADD_LABEL_TEXT"                      value="Añadir / Editar:"></property>
        <property name="TYPE_LABEL_TEXT"                     value="Tipo:"></property>
        <property name="DATE_LABEL_TEXT"                     value="Date:"></property>
        <property name="TITLE_LABEL_TEXT"                    value="Fecha:"></property>
        <property name="TOPIC_LABEL_TEXT"                    value="Tema:"></property>
        <property name="LINK_LABEL_TEXT"                     value="Enlazar:"></property>
        
        <property name="S_STYLE_FAV_BUTTON_TEXT"            value="Favicon"></property>
        <property name="S_STYLE_NAV_BUTTON_TEXT"            value="Navbar Image"></property>
        <property name="S_STYLE_LEFT_BUTTON_TEXT"            value="Imagen del pie izquierdo"></property>
        <property name="S_STYLE_RIGHT_BUTTON_TEXT"            value="Imagen de pie derecho"></property>
        <property name="OH_REMOVE_SCH_BUTTON_TEXT"           value="-"></property>
        <property name="SI_LABEL_TEXT"                        value="Programar Artículos"></property>
        <property name="SCH_ADD_BUTTON_TEXT"                   value="Añadir / Actualizar"></property>
        <property name="SCH_CLEAR_BUTTON_TEXT"                 value="Claro"></property>
        <property name="OH_START_LABEL_TEXT"                     value="Hora de inicio:"></property>
        <property name="OH_END_LABEL_TEXT"                       value="Hora de finalización:"></property>
        
        <property name="S_OH_TITLE_PANE"                    value="Horas de oficina"></property>
        <property name="S_DES_TITLE_PANE"                   value="Descripción"></property>
        <property name="S_TOP_TITLE_PANE"                   value="Los temas"></property>
        <property name="S_PRE_TITLE_PANE"                   value="Prerrequisitos"></property>
        <property name="S_OUT_TITLE_PANE"                   value="Resultados"></property>  
        <property name="S_TEX_TITLE_PANE"                   value="Libros de texto"></property>
        <property name="S_GRADED_TITLE_PANE"                value="Componentes graduados"></property>
        <property name="S_GRADING_TITLE_PANE"               value="Nota de calificación"></property>
        <property name="S_ACA_TITLE_PANE"                   value="Deshonestidad academica"></property>
        <property name="S_SPE_TITLE_PANE"                   value="Asistencia especial"></property>
        <property name="S_NAME_LABEL_TEXT"                   value="pong"></property>
        <property name="S_EMAIL_LABEL"                   value="email"></property>
        <property name="S_ROOM_LABEL"                   value="pa'Daq"></property>
        <property name="S_HOME_PAGE_LABEL"                   value="page"></property>
        
        
        
        
        <property name="S_SUBJECT_LABEL_TEXT"               value="Tema:"></property>
        <property name="S_NUMBER_LABEL_TEXT"                value="Número:"></property>
        <property name="S_SEMESTER_LABEL_TEXT"              value="Semester:"></property>
        <property name="S_YEAR_LABEL_TEXT"                  value="Año:"></property>
        <property name="S_TITLE_LABEL_TEXT"                 value="Título:"></property>
        <property name="S_EXPORT_LABEL_TEXT"                value="Exportarte:"></property>
        <property name="S_BANNER_LABEL_TEXT"                value="Bandera"></property>
        <property name="S_STYLE_LABEL_TEXT"                 value="Estilo"></property>
        <property name="S_INSTRUCTOR_LABEL_TEXT"            value="instructor"></property>
        <property name="S_EXPORT_TEXT_LABEL_TEXT"           value=".\export\CSE_219_Fall_2018\public_html"></property>
        
        
        <!-- ERROR DIALOG -->
        <property name="OH_NO_TA_SELECTED_TITLE"        value="pagh ta wIv"></property>
        <property name="OH_NO_TA_SELECTED_CONTENT"      value="qIt neH toggle vaj wIv ta"></property>

        <!-- TO SWITCH BACK TO ANOTHER LANGUAGE -->
        <property name="LANGUAGE_DIALOG_TITLE"          value="app Hol Selection"></property>
        <property name="LANGUAGE_DIALOG_HEADER_TEXT"    value="Hol wutlh"></property>
        <property name="LANGUAGE_DIALOG_CONTENT_TEXT"   value="[Hol User Interface. ghaHDaq wIv BERNARDO."></property>

        <property name="WORK_FILE_EXT"          value="*.ta"></property>
	<property name="WORK_FILE_EXT_DESC"     value="ghojmoH boQwI' teywI'"></property>

    </property_list>
    
    <!-- TDLM COMBO BOX CHOICES -->
    <property_options_list>
        <property_options name="LANGUAGE_OPTIONS">
            <option>English Hol</option>
            <option>tlhIngan</option>
        </property_options>
    </property_options_list>
</properties>